smsitai/__init__.py
smsitai/check.py
smsitai/extras/__init__.py
smsitai-0.0.2.11.dist-info/METADATA
smsitai-0.0.2.11.dist-info/WHEEL
smsitai-0.0.2.11.dist-info/top_level.txt
smsitai-0.0.2.11.dist-info/RECORD
